regoct/__init__.py
regoct/interface.py
regoct/reader.py
regoct/saveing.py
regoct/structures.py
regoct/util.py
regoct/visualiser.py
regOct-1.1.3.dist-info/METADATA
regOct-1.1.3.dist-info/WHEEL
regOct-1.1.3.dist-info/top_level.txt
regOct-1.1.3.dist-info/RECORD
