Metadata-Version: 2.1
Name: regOct
Version: 1.1.3
Summary: A module implementing octrees for python
Home-page: https://github.com/runoverPy/regOct
Author: runover
License: MIT
Platform: UNKNOWN
Classifier: Development Status :: 4 - Beta
Classifier: Intended Audience :: Developers
Classifier: License :: OSI Approved :: MIT License
Classifier: Programming Language :: Python :: 3.0
Classifier: Programming Language :: Python :: 3.8
Classifier: Programming Language :: Python :: 3.9
Requires-Python: >=3, <4
Requires-Dist: PyGLM
Requires-Dist: numpy
Requires-Dist: keyboard
Requires-Dist: glfw
Requires-Dist: PyOpenGL
Requires-Dist: tqdm
